quack_sleep_doctor/languages.py
quack_sleep_doctor/main.py
quack_sleep_doctor-0.2.0.dist-info/METADATA
quack_sleep_doctor-0.2.0.dist-info/WHEEL
quack_sleep_doctor-0.2.0.dist-info/entry_points.txt
quack_sleep_doctor-0.2.0.dist-info/RECORD
