Metadata-Version: 2.4
Name: quack-sleep-doctor
Version: 0.2.0
Summary: A small utility to remind you to go to sleep.
Requires-Python: >=3.12
